Metadata-Version: 2.1
Name: pyPhasesRecordloaderSleepEDF
Version: 0.2.0
Summary: Adds a record loaders to the pyPhases package
Home-page: https://gitlab.com/tud.ibmt.public/pyphases/pyphasesrecordloader/
Author: Franz Ehrlich
Author-email: fehrlichd@gmail.com
Classifier: Programming Language :: Python :: 3
Classifier: License :: OSI Approved :: MIT License
Classifier: Operating System :: OS Independent
Requires-Python: >=3.5
License-File: LICENSE
